{
  "description": "Fioraio storico a Como. Fiorista Como. Orchidee, piante, bouquet e composizioni floreali. Consegna a domicilio a Como e provincia. Visita il nostro negozio in Via\n  Leone Leoni 2.",
  "favicon": "//maspesfiori.it/cdn/shop/files/favicon_32x32.png?v=1613686937",
  "fetched_url": "https://maspesfiori.it/",
  "final_url": "https://maspesfiori.it/",
  "headings": {
    "h1": [
      "<img src=\"//maspesfiori.it/cdn/shop/files/Logo_130x.png?v=1613686514\"\n                     srcset=\"//maspesfiori.it/cdn/shop/files/Logo_130x.png?v=1613686514 1x, //maspesfiori.it/cdn/shop/files/Logo_130x@2x.png?v=1613686514 2x\"\n                     alt=\"Maspes Piante e Fiori\"\n                     style=\"max-width: 130px;\">"
    ],
    "h2": [
      "Appena aggiunto al carrello",
      "Benvenuti",
      "i nostri prodotti",
      "Dicono di noi",
      "Posizione"
    ]
  },
  "og_image": "https://cdn.shopify.com/s/files/1/0258/2256/0314/files/locoshare_ec6a4e7a-2353-4cb3-a47b-6dc38d6abaab.png?v=1588525872",
  "og_site_name": "Maspes Piante e Fiori",
  "og_title": "Maspes Piante e Fiori Como",
  "title": "Maspes Piante e Fiori | Fiorista a Como dal 1954 - Consegna a domicilio"
}